audio2chat/__init__.py
audio2chat/chat_builder.py
audio2chat/cli.py
audio2chat/pipeline.py
audio2chat/transcriber.py
audio2chat/transcriber_whisper.py
audio2chat/youtube_downloader.py
audio2chat/utils/__init__.py
audio2chat/utils/config.py
audio2chat/utils/file_handler.py
audio2chat/utils/logger.py
tests/__init__.py
tests/test_chat_builder.py
tests/test_pipeline.py
tests/test_whisper.py
audio2chat-0.1.0.dist-info/LICENSE
audio2chat-0.1.0.dist-info/METADATA
audio2chat-0.1.0.dist-info/WHEEL
audio2chat-0.1.0.dist-info/entry_points.txt
audio2chat-0.1.0.dist-info/top_level.txt
audio2chat-0.1.0.dist-info/RECORD
