Metadata-Version: 2.2
Name: audio2chat
Version: 0.1.0
Summary: Generate chat data from multi-speaker audio files
Home-page: https://github.com/neuralwork/audio2chat
Author: Alara Dirik
Keywords: audio,transcription,whisper,diarization,speech-to-text,chat
Classifier: Development Status :: 4 - Beta
Classifier: Intended Audience :: Developers
Classifier: License :: OSI Approved :: MIT License
Classifier: Operating System :: OS Independent
Classifier: Programming Language :: Python :: 3
Classifier: Programming Language :: Python :: 3.8
Classifier: Programming Language :: Python :: 3.9
Classifier: Programming Language :: Python :: 3.10
Classifier: Topic :: Multimedia :: Sound/Audio :: Speech
Classifier: Topic :: Scientific/Engineering :: Artificial Intelligence
Requires-Python: >=3.8
License-File: LICENSE
Requires-Dist: numpy>=1.19.0
Requires-Dist: torch>=2.1.1
Requires-Dist: transformers>=4.37.0
Requires-Dist: accelerate>=0.27.0
Requires-Dist: datasets[audio]>=2.16.0
Requires-Dist: librosa>=0.9.0
Requires-Dist: soundfile>=0.10.0
Requires-Dist: assemblyai
Requires-Dist: ffmpeg-python>=0.2.0
Requires-Dist: yt-dlp>=2023.12.30
Provides-Extra: speed
Requires-Dist: flash-attn>=2.5.0; extra == "speed"
Requires-Dist: safetensors>=0.4.1; extra == "speed"
Provides-Extra: dev
Requires-Dist: pytest>=6.0; extra == "dev"
Requires-Dist: black>=22.0; extra == "dev"
Requires-Dist: isort>=5.0; extra == "dev"
Requires-Dist: flake8>=4.0; extra == "dev"
Dynamic: author
Dynamic: classifier
Dynamic: description
Dynamic: description-content-type
Dynamic: home-page
Dynamic: keywords
Dynamic: provides-extra
Dynamic: requires-dist
Dynamic: requires-python
Dynamic: summary
